vsutil/__init__.py
vsutil/_metadata.py
vsutil/clips.py
vsutil/func.py
vsutil/info.py
vsutil/py.typed
vsutil/types.py
vsutil-0.8.0.dist-info/LICENSE
vsutil-0.8.0.dist-info/METADATA
vsutil-0.8.0.dist-info/WHEEL
vsutil-0.8.0.dist-info/top_level.txt
vsutil-0.8.0.dist-info/RECORD
